metawards/__init__.py
metawards/_demographic.py
metawards/_demographics.py
metawards/_disease.py
metawards/_infections.py
metawards/_inputfiles.py
metawards/_interpret.py
metawards/_link.py
metawards/_links.py
metawards/_network.py
metawards/_networks.py
metawards/_node.py
metawards/_nodes.py
metawards/_outputfiles.py
metawards/_parameters.py
metawards/_population.py
metawards/_run.py
metawards/_variableset.py
metawards/_version.py
metawards/_ward.py
metawards/_wardid.py
metawards/_wardinfo.py
metawards/_wards.py
metawards/_workspace.py
metawards/__pycache__/__init__.cpython-39.pyc
metawards/__pycache__/_demographic.cpython-39.pyc
metawards/__pycache__/_demographics.cpython-39.pyc
metawards/__pycache__/_disease.cpython-39.pyc
metawards/__pycache__/_infections.cpython-39.pyc
metawards/__pycache__/_inputfiles.cpython-39.pyc
metawards/__pycache__/_interpret.cpython-39.pyc
metawards/__pycache__/_link.cpython-39.pyc
metawards/__pycache__/_links.cpython-39.pyc
metawards/__pycache__/_network.cpython-39.pyc
metawards/__pycache__/_networks.cpython-39.pyc
metawards/__pycache__/_node.cpython-39.pyc
metawards/__pycache__/_nodes.cpython-39.pyc
metawards/__pycache__/_outputfiles.cpython-39.pyc
metawards/__pycache__/_parameters.cpython-39.pyc
metawards/__pycache__/_population.cpython-39.pyc
metawards/__pycache__/_run.cpython-39.pyc
metawards/__pycache__/_variableset.cpython-39.pyc
metawards/__pycache__/_version.cpython-39.pyc
metawards/__pycache__/_ward.cpython-39.pyc
metawards/__pycache__/_wardid.cpython-39.pyc
metawards/__pycache__/_wardinfo.cpython-39.pyc
metawards/__pycache__/_wards.cpython-39.pyc
metawards/__pycache__/_workspace.cpython-39.pyc
metawards/analysis/__init__.py
metawards/analysis/_animate_plots.py
metawards/analysis/_summary_plot.py
metawards/analysis/__pycache__/__init__.cpython-39.pyc
metawards/analysis/__pycache__/_animate_plots.cpython-39.pyc
metawards/analysis/__pycache__/_summary_plot.cpython-39.pyc
metawards/app/__init__.py
metawards/app/run.py
metawards-1.6.2.dist-info/LICENSE.txt
metawards-1.6.2.dist-info/METADATA
metawards-1.6.2.dist-info/WHEEL
metawards-1.6.2.dist-info/entry_points.txt
metawards-1.6.2.dist-info/top_level.txt
metawards-1.6.2.dist-info/RECORD
