Metadata-Version: 2.1
Name: metawards
Version: 1.6.2
Summary: MetaWards disease metapopulation modelling
Home-page: https://github.com/metawards/metawards
Author: Leon Danon (original C code), Christopher Woods (Python port)
Author-email: l.danon@bristol.ac.uk, Christopher.Woods@bristol.ac.uk
License: GPL3
Project-URL: Documentation, https://metawards.org
Project-URL: Code, https://github.com/metawards/MetaWards
Project-URL: Issue tracker, https://github.com/metawards/MetaWards/issues
Platform: UNKNOWN
Classifier: Development Status :: 4 - Beta
Classifier: License :: OSI Approved :: GNU General Public License v3 (GPLv3)
Classifier: Intended Audience :: Education
Classifier: Intended Audience :: Science/Research
Classifier: Topic :: Scientific/Engineering
Classifier: Natural Language :: English
Classifier: Operating System :: OS Independent
Classifier: Operating System :: MacOS :: MacOS X
Classifier: Operating System :: Microsoft :: Windows
Classifier: Operating System :: POSIX :: Linux
Classifier: Programming Language :: C
Classifier: Programming Language :: Cython
Classifier: Programming Language :: Python
Classifier: Programming Language :: Python :: 3
Classifier: Programming Language :: Python :: 3.7
Classifier: Programming Language :: Python :: 3.8
Classifier: Programming Language :: Python :: 3.9
Classifier: Programming Language :: Python :: 3 :: Only
Classifier: Programming Language :: Python :: Implementation :: CPython
Requires-Python: >=3.7
License-File: LICENSE.txt
Requires-Dist: dateparser (>=0.7.0)
Requires-Dist: configargparse (>=1.2.0)
Requires-Dist: lazy-import (>=0.2.2)
Requires-Dist: rich (>=4.2.0)
Requires-Dist: yaspin (>=0.18.0)
Provides-Extra: dev
Requires-Dist: pytest (>=5.1) ; extra == 'dev'
Requires-Dist: pytest-cov (>=2.2.0) ; extra == 'dev'
Requires-Dist: flake8 (>=3.7) ; extra == 'dev'
Requires-Dist: cython (>=0.29.13) ; extra == 'dev'
Requires-Dist: numpy (>=1.17.2) ; extra == 'dev'
Requires-Dist: sphinx (==4.2.0) ; extra == 'dev'
Requires-Dist: sphinx-issues ; extra == 'dev'
Requires-Dist: sphinx-rtd-theme ; extra == 'dev'
Requires-Dist: sphinxcontrib-programoutput ; extra == 'dev'
Provides-Extra: docs
Requires-Dist: sphinx ; extra == 'docs'
Requires-Dist: sphinx-rtd-theme ; extra == 'docs'
